ezclimate/__init__.py
ezclimate/analysis.py
ezclimate/bau.py
ezclimate/cost.py
ezclimate/damage.py
ezclimate/damage_simulation.py
ezclimate/forcing.py
ezclimate/optimization.py
ezclimate/storage_tree.py
ezclimate/tools.py
ezclimate/tree.py
ezclimate/utility.py
ezclimate-2.0.7.dist-info/LICENSE
ezclimate-2.0.7.dist-info/METADATA
ezclimate-2.0.7.dist-info/WHEEL
ezclimate-2.0.7.dist-info/top_level.txt
ezclimate-2.0.7.dist-info/zip-safe
ezclimate-2.0.7.dist-info/RECORD
