Metadata-Version: 2.1
Name: ezclimate
Version: 2.0.7
Summary: EZ-Climate model
Home-page: http://github.com/Litterman/EZClimate
Author: Kent Daniel, Robert Litterman, Gernot Wagner
Author-email: UNKNOWN
License: MIT
Requires-Dist: numpy
